dataframe2ndjson.py
dataframe2ndjson-0.0.1.dist-info/LICENSE
dataframe2ndjson-0.0.1.dist-info/METADATA
dataframe2ndjson-0.0.1.dist-info/WHEEL
dataframe2ndjson-0.0.1.dist-info/top_level.txt
dataframe2ndjson-0.0.1.dist-info/RECORD
