Metadata-Version: 2.1
Name: dataframe2ndjson
Version: 0.0.1
Summary: dataframe2ndjson converts a dataframe to ndjson file
Home-page: UNKNOWN
Author: Nishank Parashar
License: UNKNOWN
Platform: UNKNOWN
Classifier: Programming Language :: Python :: 3
Classifier: License :: OSI Approved :: MIT License
Classifier: Operating System :: OS Independent
Requires-Python: >=3.6
License-File: LICENSE
